ioelin_iot_ui_mcp_server/__init__.py
ioelin_iot_ui_mcp_server/static/back.png
ioelin_iot_ui_mcp_server/static/fan.png
ioelin_iot_ui_mcp_server/static/fan1.png
ioelin_iot_ui_mcp_server/static/fan_off.png
ioelin_iot_ui_mcp_server/static/logo.png
ioelin_iot_ui_mcp_server/static/主卧.png
ioelin_iot_ui_mcp_server/static/儿童房.png
ioelin_iot_ui_mcp_server/static/内卫.png
ioelin_iot_ui_mcp_server/static/卫生间.png
ioelin_iot_ui_mcp_server/static/厨房.png
ioelin_iot_ui_mcp_server/static/客卫.png
ioelin_iot_ui_mcp_server/static/客厅.png
ioelin_iot_ui_mcp_server/static/次卧.png
ioelin_iot_ui_mcp_server/static/阳台.png
ioelin_iot_ui_mcp_server/ui.py
ioelin_iot_ui_mcp_server-0.1.2.dist-info/WHEEL
ioelin_iot_ui_mcp_server-0.1.2.dist-info/entry_points.txt
ioelin_iot_ui_mcp_server-0.1.2.dist-info/METADATA
ioelin_iot_ui_mcp_server-0.1.2.dist-info/RECORD
