Metadata-Version: 2.3
Name: ioelin-iot-ui-mcp-server
Version: 0.1.2
Summary: Add your description here
Author: andy
Author-email: andy <562483069@qq.com>
Requires-Dist: mcp[cli]>=1.12.4
Requires-Dist: pillow>=11.3.0
Requires-Python: >=3.13
